http_api_tool/__init__.py
http_api_tool/__main__.py
http_api_tool/_version.py
http_api_tool/cli.py
http_api_tool/verifier.py
http_api_tool-1.0.4.dist-info/METADATA
http_api_tool-1.0.4.dist-info/WHEEL
http_api_tool-1.0.4.dist-info/entry_points.txt
http_api_tool-1.0.4.dist-info/licenses/LICENSE
http_api_tool-1.0.4.dist-info/RECORD
