Metadata-Version: 2.4
Name: http-api-tool
Version: 1.0.4
Summary: A Python HTTP/HTTPS API testing tool for GitHub Actions and CLI usage
Project-URL: Homepage, https://github.com/lfreleng-actions/http-api-tool-docker
Project-URL: Repository, https://github.com/lfreleng-actions/http-api-tool-docker
Project-URL: Documentation, https://github.com/lfreleng-actions/http-api-tool-docker/blob/main/README.md
Project-URL: Bug Tracker, https://github.com/lfreleng-actions/http-api-tool-docker/issues
Author-email: Matthew Watkins <93649628+ModeSevenIndustrialSolutions@users.noreply.github.com>
Maintainer-email: Matthew Watkins <93649628+ModeSevenIndustrialSolutions@users.noreply.github.com>
License: Apache-2.0
License-File: LICENSE
Keywords: api,curl,github-actions,health-check,http,monitoring,testing,verification
Classifier: Development Status :: 5 - Production/Stable
Classifier: Environment :: Console
Classifier: Intended Audience :: Developers
Classifier: Intended Audience :: System Administrators
Classifier: License :: OSI Approved :: Apache Software License
Classifier: Operating System :: OS Independent
Classifier: Programming Language :: Python :: 3
Classifier: Programming Language :: Python :: 3.10
Classifier: Programming Language :: Python :: 3.11
Classifier: Programming Language :: Python :: 3.12
Classifier: Programming Language :: Python :: 3.13
Classifier: Programming Language :: Python :: 3.14
Classifier: Topic :: Internet :: WWW/HTTP
Classifier: Topic :: Software Development :: Testing
Classifier: Topic :: System :: Monitoring
Classifier: Topic :: Utilities
Requires-Python: >=3.10
Requires-Dist: certifi>=2025.6.15
Requires-Dist: pycurl>=7.45.0
Requires-Dist: requests>=2.32.4
Requires-Dist: typer>=0.9.0
Provides-Extra: dev
Requires-Dist: bandit>=1.8.0; extra == 'dev'
Requires-Dist: black>=24.0.0; extra == 'dev'
Requires-Dist: coverage[toml]>=7.9.1; extra == 'dev'
Requires-Dist: flake8>=7.0.0; extra == 'dev'
Requires-Dist: interrogate>=1.5.0; extra == 'dev'
Requires-Dist: isort>=5.13.0; extra == 'dev'
Requires-Dist: mypy>=1.11.0; extra == 'dev'
Requires-Dist: pre-commit>=4.0.0; extra == 'dev'
Requires-Dist: pytest-cov>=6.2.1; extra == 'dev'
Requires-Dist: pytest>=8.0.0; extra == 'dev'
Provides-Extra: test
Requires-Dist: coverage[toml]>=7.9.1; extra == 'test'
Requires-Dist: pytest-cov>=6.2.1; extra == 'test'
Requires-Dist: pytest>=8.0.0; extra == 'test'
Requires-Dist: requests>=2.32.4; extra == 'test'
Requires-Dist: responses>=0.25.0; extra == 'test'
